pyqt_checkbox_list_widget/__init__.py
pyqt_checkbox_list_widget/checkBoxListWidget.py
pyqt_checkbox_list_widget-0.0.1.dist-info/LICENSE
pyqt_checkbox_list_widget-0.0.1.dist-info/METADATA
pyqt_checkbox_list_widget-0.0.1.dist-info/WHEEL
pyqt_checkbox_list_widget-0.0.1.dist-info/top_level.txt
pyqt_checkbox_list_widget-0.0.1.dist-info/RECORD
